{
  "result": "success",
  "data": {
    "Buses": [
      {
        "RouteId": 3,
        "BusId": 2139,
        "ETA": 42,
        "LastStopId": 323,
        "NextStopId": 324,
        "LatLng": {
          "Latitude": -31.956285937628177,
          "Longitude": 115.87344781247009
        },
        "ImageUrl": "/Portals/0/Asset/Images/LiveCatTimes/yellowCat/bus_291.png",
        "ImageWidth": 40,
        "ImageHeight": 40
      },
      {
        "RouteId": 8,
        "BusId": 2141,
        "ETA": 181,
        "LastStopId": 811,
        "NextStopId": 812,
        "LatLng": {
          "Latitude": -31.940490459809375,
          "Longitude": 115.84122990315441
        },
        "ImageUrl": "/Portals/0/Asset/Images/LiveCatTimes/greenCat/bus_130.png",
        "ImageWidth": 40,
        "ImageHeight": 40
      },
      {
        "RouteId": 3,
        "BusId": 2142,
        "ETA": 16,
        "LastStopId": 332,
        "NextStopId": 333,
        "LatLng": {
          "Latitude": -31.946133955953332,
          "Longitude": 115.84231186590212
        },
        "ImageUrl": "/Portals/0/Asset/Images/LiveCatTimes/yellowCat/bus_291.png",
        "ImageWidth": 40,
        "ImageHeight": 40
      },
      {
        "RouteId": 1,
        "BusId": 2143,
        "ETA": 25,
        "LastStopId": 109,
        "NextStopId": 110,
        "LatLng": {
          "Latitude": -31.94736698007052,
          "Longitude": 115.86071916067543
        },
        "ImageUrl": "/Portals/0/Asset/Images/LiveCatTimes/blueCat/bus_298.png",
        "ImageWidth": 40,
        "ImageHeight": 40
      },
      {
        "RouteId": 2,
        "BusId": 2145,
        "ETA": 10,
        "LastStopId": 213,
        "NextStopId": 215,
        "LatLng": {
          "Latitude": -31.952964919325456,
          "Longitude": 115.8610541952645
        },
        "ImageUrl": "/Portals/0/Asset/Images/LiveCatTimes/redCat/bus_21.png",
        "ImageWidth": 40,
        "ImageHeight": 40
      },
      {
        "RouteId": 2,
        "BusId": 2610,
        "ETA": 137,
        "LastStopId": 206,
        "NextStopId": 207,
        "LatLng": {
          "Latitude": -31.95871036787759,
          "Longitude": 115.87795895863822
        },
        "ImageUrl": "/Portals/0/Asset/Images/LiveCatTimes/redCat/bus_94.png",
        "ImageWidth": 40,
        "ImageHeight": 40
      },
      {
        "RouteId": 2,
        "BusId": 2617,
        "ETA": 153,
        "LastStopId": 229,
        "NextStopId": 231,
        "LatLng": {
          "Latitude": -31.952309531064156,
          "Longitude": 115.8570053498913
        },
        "ImageUrl": "/Portals/0/Asset/Images/LiveCatTimes/redCat/bus_110.png",
        "ImageWidth": 40,
        "ImageHeight": 40
      },
      {
        "RouteId": 2,
        "BusId": 2618,
        "ETA": 48,
        "LastStopId": 204,
        "NextStopId": 205,
        "LatLng": {
          "Latitude": -31.95761,
          "Longitude": 115.87224
        },
        "ImageUrl": "/Portals/0/Asset/Images/LiveCatTimes/redCat/bus_.png",
        "ImageWidth": 40,
        "ImageHeight": 40
      },
      {
        "RouteId": 2,
        "BusId": 2619,
        "ETA": 115,
        "LastStopId": 217,
        "NextStopId": 218,
        "LatLng": {
          "Latitude": -31.95331357417125,
          "Longitude": 115.85610503879023
        },
        "ImageUrl": "/Portals/0/Asset/Images/LiveCatTimes/redCat/bus_291.png",
        "ImageWidth": 40,
        "ImageHeight": 40
      },
      {
        "RouteId": 3,
        "BusId": 2620,
        "ETA": 11,
        "LastStopId": 311,
        "NextStopId": 312,
        "LatLng": {
          "Latitude": -31.953172289213054,
          "Longitude": 115.87712020956555
        },
        "ImageUrl": "/Portals/0/Asset/Images/LiveCatTimes/yellowCat/bus_267.png",
        "ImageWidth": 40,
        "ImageHeight": 40
      },
      {
        "RouteId": 3,
        "BusId": 2622,
        "ETA": 10,
        "LastStopId": 335,
        "NextStopId": 336,
        "LatLng": {
          "Latitude": -31.948254608277608,
          "Longitude": 115.84921782635602
        },
        "ImageUrl": "/Portals/0/Asset/Images/LiveCatTimes/yellowCat/bus_111.png",
        "ImageWidth": 40,
        "ImageHeight": 40
      },
      {
        "RouteId": 2,
        "BusId": 2623,
        "ETA": 56,
        "LastStopId": 224,
        "NextStopId": 225,
        "LatLng": {
          "Latitude": -31.949543033802478,
          "Longitude": 115.83926851226765
        },
        "ImageUrl": "/Portals/0/Asset/Images/LiveCatTimes/redCat/bus_200.png",
        "ImageWidth": 40,
        "ImageHeight": 40
      },
      {
        "RouteId": 2,
        "BusId": 2627,
        "ETA": 27,
        "LastStopId": 210,
        "NextStopId": 211,
        "LatLng": {
          "Latitude": -31.958097581294755,
          "Longitude": 115.87086627317225
        },
        "ImageUrl": "/Portals/0/Asset/Images/LiveCatTimes/redCat/bus_291.png",
        "ImageWidth": 40,
        "ImageHeight": 40
      },
      {
        "RouteId": 1,
        "BusId": 2628,
        "ETA": 3,
        "LastStopId": 117,
        "NextStopId": 122,
        "LatLng": {
          "Latitude": -31.95619616153775,
          "Longitude": 115.85405346947897
        },
        "ImageUrl": "/Portals/0/Asset/Images/LiveCatTimes/blueCat/bus_296.png",
        "ImageWidth": 40,
        "ImageHeight": 40
      },
      {
        "RouteId": 1,
        "BusId": 2629,
        "ETA": -83,
        "LastStopId": 117,
        "NextStopId": 122,
        "LatLng": {
          "Latitude": -31.956549201469734,
          "Longitude": 115.85489660910564
        },
        "ImageUrl": "/Portals/0/Asset/Images/LiveCatTimes/blueCat/bus_296.png",
        "ImageWidth": 40,
        "ImageHeight": 40
      },
      {
        "RouteId": 1,
        "BusId": 2630,
        "ETA": 210,
        "LastStopId": 198,
        "NextStopId": 119,
        "LatLng": {
          "Latitude": -31.95695,
          "Longitude": 115.85619
        },
        "ImageUrl": "/Portals/0/Asset/Images/LiveCatTimes/blueCat/bus_.png",
        "ImageWidth": 40,
        "ImageHeight": 40
      },
      {
        "RouteId": 1,
        "BusId": 2631,
        "ETA": 78,
        "LastStopId": 119,
        "NextStopId": 106,
        "LatLng": {
          "Latitude": -31.955020298091558,
          "Longitude": 115.8600979464764
        },
        "ImageUrl": "/Portals/0/Asset/Images/LiveCatTimes/blueCat/bus_22.png",
        "ImageWidth": 40,
        "ImageHeight": 40
      },
      {
        "RouteId": 3,
        "BusId": 2632,
        "ETA": -21,
        "LastStopId": 314,
        "NextStopId": 315,
        "LatLng": {
          "Latitude": -31.95097000000117,
          "Longitude": 115.87121001261772
        },
        "ImageUrl": "/Portals/0/Asset/Images/LiveCatTimes/yellowCat/bus_269.png",
        "ImageWidth": 40,
        "ImageHeight": 40
      },
      {
        "RouteId": 2,
        "BusId": 2633,
        "ETA": -6,
        "LastStopId": 218,
        "NextStopId": 219,
        "LatLng": {
          "Latitude": -31.95190155276202,
          "Longitude": 115.85179327207115
        },
        "ImageUrl": "/Portals/0/Asset/Images/LiveCatTimes/redCat/bus_291.png",
        "ImageWidth": 40,
        "ImageHeight": 40
      },
      {
        "RouteId": 3,
        "BusId": 2635,
        "ETA": -4,
        "LastStopId": 303,
        "NextStopId": 304,
        "LatLng": {
          "Latitude": -31.95258,
          "Longitude": 115.8625
        },
        "ImageUrl": "/Portals/0/Asset/Images/LiveCatTimes/yellowCat/bus_.png",
        "ImageWidth": 40,
        "ImageHeight": 40
      },
      {
        "RouteId": 8,
        "BusId": 2665,
        "ETA": -143,
        "LastStopId": 820,
        "NextStopId": 801,
        "LatLng": {
          "Latitude": -31.95471460075073,
          "Longitude": 115.85648941345285
        },
        "ImageUrl": "/Portals/0/Asset/Images/LiveCatTimes/greenCat/bus_290.png",
        "ImageWidth": 40,
        "ImageHeight": 40
      },
      {
        "RouteId": 2,
        "BusId": 2666,
        "ETA": -1,
        "LastStopId": 206,
        "NextStopId": 207,
        "LatLng": {
          "Latitude": -31.95766433394614,
          "Longitude": 115.8780316069756
        },
        "ImageUrl": "/Portals/0/Asset/Images/LiveCatTimes/redCat/bus_265.png",
        "ImageWidth": 40,
        "ImageHeight": 40
      },
      {
        "RouteId": 3,
        "BusId": 2670,
        "ETA": -283,
        "LastStopId": 314,
        "NextStopId": 315,
        "LatLng": {
          "Latitude": -31.95097854958378,
          "Longitude": 115.87049776708085
        },
        "ImageUrl": "/Portals/0/Asset/Images/LiveCatTimes/yellowCat/bus_91.png",
        "ImageWidth": 40,
        "ImageHeight": 40
      },
      {
        "RouteId": 3,
        "BusId": 2671,
        "ETA": 10,
        "LastStopId": 327,
        "NextStopId": 328,
        "LatLng": {
          "Latitude": -31.95184846283049,
          "Longitude": 115.85990558062265
        },
        "ImageUrl": "/Portals/0/Asset/Images/LiveCatTimes/yellowCat/bus_292.png",
        "ImageWidth": 40,
        "ImageHeight": 40
      },
      {
        "RouteId": 8,
        "BusId": 2672,
        "ETA": 38,
        "LastStopId": 807,
        "NextStopId": 808,
        "LatLng": {
          "Latitude": -31.94791083609481,
          "Longitude": 115.84252713847104
        },
        "ImageUrl": "/Portals/0/Asset/Images/LiveCatTimes/greenCat/bus_19.png",
        "ImageWidth": 40,
        "ImageHeight": 40
      },
      {
        "RouteId": 8,
        "BusId": 2673,
        "ETA": 229,
        "LastStopId": 811,
        "NextStopId": 812,
        "LatLng": {
          "Latitude": -31.94061115032851,
          "Longitude": 115.84139874109547
        },
        "ImageUrl": "/Portals/0/Asset/Images/LiveCatTimes/greenCat/bus_130.png",
        "ImageWidth": 40,
        "ImageHeight": 40
      },
      {
        "RouteId": 2,
        "BusId": 2674,
        "ETA": 41,
        "LastStopId": 227,
        "NextStopId": 228,
        "LatLng": {
          "Latitude": -31.949244297021274,
          "Longitude": 115.84764110472649
        },
        "ImageUrl": "/Portals/0/Asset/Images/LiveCatTimes/redCat/bus_110.png",
        "ImageWidth": 40,
        "ImageHeight": 40
      },
      {
        "RouteId": 8,
        "BusId": 2675,
        "ETA": 200,
        "LastStopId": 820,
        "NextStopId": 801,
        "LatLng": {
          "Latitude": -31.956388303663463,
          "Longitude": 115.85494958613056
        },
        "ImageUrl": "/Portals/0/Asset/Images/LiveCatTimes/greenCat/bus_291.png",
        "ImageWidth": 40,
        "ImageHeight": 40
      },
      {
        "RouteId": 2,
        "BusId": 2676,
        "ETA": 185,
        "LastStopId": 231,
        "NextStopId": 201,
        "LatLng": {
          "Latitude": -31.95203062209974,
          "Longitude": 115.86044852255026
        },
        "ImageUrl": "/Portals/0/Asset/Images/LiveCatTimes/redCat/bus_291.png",
        "ImageWidth": 40,
        "ImageHeight": 40
      }
    ],
    "Stops": [
      {
        "RouteStopId": 101,
        "Name": "N/A",
        "Description": "Blue",
        "ETA": -1603863058
      },
      {
        "RouteStopId": 102,
        "Name": "N/A",
        "Description": "Blue",
        "ETA": -1603863058
      },
      {
        "RouteStopId": 103,
        "Name": "N/A",
        "Description": "Blue",
        "ETA": -1603863058
      },
      {
        "RouteStopId": 104,
        "Name": "N/A",
        "Description": "Blue",
        "ETA": -1603863058
      },
      {
        "RouteStopId": 105,
        "Name": "N/A",
        "Description": "Blue",
        "ETA": -1603863058
      },
      {
        "RouteStopId": 106,
        "Name": "Beaufort St Bridge",
        "Description": "Blue",
        "ETA": 79
      },
      {
        "RouteStopId": 107,
        "Name": "Museum",
        "Description": "Blue",
        "ETA": 179
      },
      {
        "RouteStopId": 108,
        "Name": "Arts Centre",
        "Description": "Blue",
        "ETA": 279
      },
      {
        "RouteStopId": 109,
        "Name": "Central Institute",
        "Description": "Blue",
        "ETA": 379
      },
      {
        "RouteStopId": 110,
        "Name": "Aberdeen Street",
        "Description": "Blue",
        "ETA": 26
      },
      {
        "RouteStopId": 111,
        "Name": "Francis Street",
        "Description": "Blue",
        "ETA": 126
      },
      {
        "RouteStopId": 112,
        "Name": "Russell Square",
        "Description": "Blue",
        "ETA": 226
      },
      {
        "RouteStopId": 113,
        "Name": "Northbridge",
        "Description": "Blue",
        "ETA": 326
      },
      {
        "RouteStopId": 114,
        "Name": "James Street",
        "Description": "Blue",
        "ETA": 426
      },
      {
        "RouteStopId": 116,
        "Name": "Horseshoe Bridge",
        "Description": "Blue",
        "ETA": 526
      },
      {
        "RouteStopId": 117,
        "Name": "Perth Underground",
        "Description": "Blue",
        "ETA": 626
      },
      {
        "RouteStopId": 118,
        "Name": "N/A",
        "Description": "Blue",
        "ETA": -1603863058
      },
      {
        "RouteStopId": 119,
        "Name": "Barrack Square",
        "Description": "Blue",
        "ETA": 211
      },
      {
        "RouteStopId": 120,
        "Name": "N/A",
        "Description": "Blue",
        "ETA": -1603863058
      },
      {
        "RouteStopId": 121,
        "Name": "N/A",
        "Description": "Blue",
        "ETA": -1603863058
      },
      {
        "RouteStopId": 122,
        "Name": "Elizabeth Quay Bus Station",
        "Description": "Blue",
        "ETA": -82
      },
      {
        "RouteStopId": 123,
        "Name": "N/A",
        "Description": "Blue",
        "ETA": -1603863058
      },
      {
        "RouteStopId": 198,
        "Name": "N/A",
        "Description": "Blue",
        "ETA": 278
      },
      {
        "RouteStopId": 199,
        "Name": "N/A",
        "Description": "Blue",
        "ETA": -1603863058
      },
      {
        "RouteStopId": 201,
        "Name": "Murray Street",
        "Description": "Red",
        "ETA": 186
      },
      {
        "RouteStopId": 202,
        "Name": "Royal Perth Hospital",
        "Description": "Red",
        "ETA": 286
      },
      {
        "RouteStopId": 203,
        "Name": "Mercedes College",
        "Description": "Red",
        "ETA": 386
      },
      {
        "RouteStopId": 204,
        "Name": "Bennet Street",
        "Description": "Red",
        "ETA": 486
      },
      {
        "RouteStopId": 205,
        "Name": "Queens Gardens",
        "Description": "Red",
        "ETA": 49
      },
      {
        "RouteStopId": 206,
        "Name": "WACA",
        "Description": "Red",
        "ETA": 179
      },
      {
        "RouteStopId": 207,
        "Name": "Don Aitken Centre",
        "Description": "Red",
        "ETA": 0
      },
      {
        "RouteStopId": 208,
        "Name": "Plain Street",
        "Description": "Red",
        "ETA": 100
      },
      {
        "RouteStopId": 209,
        "Name": "Wellington Square",
        "Description": "Red",
        "ETA": 200
      },
      {
        "RouteStopId": 210,
        "Name": "Carlton",
        "Description": "Red",
        "ETA": 330
      },
      {
        "RouteStopId": 211,
        "Name": "Perth Mint",
        "Description": "Red",
        "ETA": 28
      },
      {
        "RouteStopId": 212,
        "Name": "Victoria Avenue",
        "Description": "Red",
        "ETA": 128
      },
      {
        "RouteStopId": 213,
        "Name": "Town Hall",
        "Description": "Red",
        "ETA": 248
      },
      {
        "RouteStopId": 214,
        "Name": "Murray St Mall East",
        "Description": "Red",
        "ETA": -1603863058
      },
      {
        "RouteStopId": 215,
        "Name": "Forrest Place",
        "Description": "Red",
        "ETA": 11
      },
      {
        "RouteStopId": 216,
        "Name": "Perth Underground",
        "Description": "Red",
        "ETA": 141
      },
      {
        "RouteStopId": 217,
        "Name": "Central Park",
        "Description": "Red",
        "ETA": 241
      },
      {
        "RouteStopId": 218,
        "Name": "His Majesty's",
        "Description": "Red",
        "ETA": 116
      },
      {
        "RouteStopId": 219,
        "Name": "QV1",
        "Description": "Red",
        "ETA": -5
      },
      {
        "RouteStopId": 220,
        "Name": "Freeway",
        "Description": "Red",
        "ETA": -1603863058
      },
      {
        "RouteStopId": 221,
        "Name": "Parliament",
        "Description": "Red",
        "ETA": 94
      },
      {
        "RouteStopId": 222,
        "Name": "Emerald Tce",
        "Description": "Red",
        "ETA": 194
      },
      {
        "RouteStopId": 223,
        "Name": "West Perth",
        "Description": "Red",
        "ETA": 294
      },
      {
        "RouteStopId": 224,
        "Name": "Outram Street",
        "Description": "Red",
        "ETA": 379
      },
      {
        "RouteStopId": 225,
        "Name": "Ord Street",
        "Description": "Red",
        "ETA": 57
      },
      {
        "RouteStopId": 226,
        "Name": "Havelock Street",
        "Description": "Red",
        "ETA": 157
      },
      {
        "RouteStopId": 227,
        "Name": "Gordon Street",
        "Description": "Red",
        "ETA": 327
      },
      {
        "RouteStopId": 228,
        "Name": "Milligan Street",
        "Description": "Red",
        "ETA": 42
      },
      {
        "RouteStopId": 229,
        "Name": "Raine Square",
        "Description": "Red",
        "ETA": 202
      },
      {
        "RouteStopId": 230,
        "Name": "Wellington Street Bus Station",
        "Description": "Red",
        "ETA": -1603863058
      },
      {
        "RouteStopId": 231,
        "Name": "Perth Train Station",
        "Description": "Red",
        "ETA": 154
      },
      {
        "RouteStopId": 232,
        "Name": "Perth Arena",
        "Description": "Red",
        "ETA": -1603863058
      },
      {
        "RouteStopId": 299,
        "Name": "Temporary Stop",
        "Description": "Red",
        "ETA": -1603863058
      },
      {
        "RouteStopId": 302,
        "Name": "Yagan Sq.",
        "Description": "Yellow",
        "ETA": 96
      },
      {
        "RouteStopId": 303,
        "Name": "Perth Train Station (Yellow)",
        "Description": "Yellow",
        "ETA": 181
      },
      {
        "RouteStopId": 304,
        "Name": "Pier Street",
        "Description": "Yellow",
        "ETA": -3
      },
      {
        "RouteStopId": 305,
        "Name": "Royal Perth Hospital North",
        "Description": "Yellow",
        "ETA": 82
      },
      {
        "RouteStopId": 306,
        "Name": "Wellington Fair",
        "Description": "Yellow",
        "ETA": 167
      },
      {
        "RouteStopId": 307,
        "Name": "Wellington Square North",
        "Description": "Yellow",
        "ETA": 252
      },
      {
        "RouteStopId": 308,
        "Name": "Police Traffic Branch",
        "Description": "Yellow",
        "ETA": 337
      },
      {
        "RouteStopId": 309,
        "Name": "Main Roads",
        "Description": "Yellow",
        "ETA": 422
      },
      {
        "RouteStopId": 310,
        "Name": "East Perth Cemeteries",
        "Description": "Yellow",
        "ETA": 507
      },
      {
        "RouteStopId": 311,
        "Name": "Haig Park Circle",
        "Description": "Yellow",
        "ETA": 592
      },
      {
        "RouteStopId": 312,
        "Name": "Regal Place",
        "Description": "Yellow",
        "ETA": 12
      },
      {
        "RouteStopId": 313,
        "Name": "Education Department",
        "Description": "Yellow",
        "ETA": 97
      },
      {
        "RouteStopId": 314,
        "Name": "Health Department",
        "Description": "Yellow",
        "ETA": 182
      },
      {
        "RouteStopId": 315,
        "Name": "Claisebrook Station",
        "Description": "Yellow",
        "ETA": -20
      },
      {
        "RouteStopId": 316,
        "Name": "Royal Street Car Park",
        "Description": "Yellow",
        "ETA": 25
      },
      {
        "RouteStopId": 317,
        "Name": "Central Institute",
        "Description": "Yellow",
        "ETA": 110
      },
      {
        "RouteStopId": 318,
        "Name": "Royal Square",
        "Description": "Yellow",
        "ETA": 195
      },
      {
        "RouteStopId": 319,
        "Name": "Victoria Gardens",
        "Description": "Yellow",
        "ETA": 280
      },
      {
        "RouteStopId": 320,
        "Name": "Nile Street",
        "Description": "Yellow",
        "ETA": 365
      },
      {
        "RouteStopId": 321,
        "Name": "Don Aitken Centre",
        "Description": "Yellow",
        "ETA": 450
      },
      {
        "RouteStopId": 322,
        "Name": "Plain Street",
        "Description": "Yellow",
        "ETA": 535
      },
      {
        "RouteStopId": 323,
        "Name": "Wellington Square",
        "Description": "Yellow",
        "ETA": 620
      },
      {
        "RouteStopId": 324,
        "Name": "Hill Street",
        "Description": "Yellow",
        "ETA": 43
      },
      {
        "RouteStopId": 325,
        "Name": "Lord Street",
        "Description": "Yellow",
        "ETA": 128
      },
      {
        "RouteStopId": 326,
        "Name": "Royal Perth Hospital South",
        "Description": "Yellow",
        "ETA": 213
      },
      {
        "RouteStopId": 327,
        "Name": "Western Power",
        "Description": "Yellow",
        "ETA": 298
      },
      {
        "RouteStopId": 328,
        "Name": "Forrest Place",
        "Description": "Yellow",
        "ETA": 11
      },
      {
        "RouteStopId": 329,
        "Name": "Raine Square",
        "Description": "Yellow",
        "ETA": 96
      },
      {
        "RouteStopId": 330,
        "Name": "Perth Arena",
        "Description": "Yellow",
        "ETA": 141
      },
      {
        "RouteStopId": 331,
        "Name": "Sutherland Street",
        "Description": "Yellow",
        "ETA": 226
      },
      {
        "RouteStopId": 332,
        "Name": "Colin Street North",
        "Description": "Yellow",
        "ETA": 396
      },
      {
        "RouteStopId": 333,
        "Name": "Thomas Street",
        "Description": "Yellow",
        "ETA": 17
      },
      {
        "RouteStopId": 334,
        "Name": "Harold Boas North",
        "Description": "Yellow",
        "ETA": 102
      },
      {
        "RouteStopId": 335,
        "Name": "Sutherland Street",
        "Description": "Yellow",
        "ETA": 187
      },
      {
        "RouteStopId": 336,
        "Name": "Perth Arena",
        "Description": "Yellow",
        "ETA": 11
      },
      {
        "RouteStopId": 337,
        "Name": "Harold Boas South",
        "Description": "Yellow",
        "ETA": 311
      },
      {
        "RouteStopId": 401,
        "Name": "Perth Underground",
        "Description": "Red Short",
        "ETA": 458
      },
      {
        "RouteStopId": 402,
        "Name": "Central Park",
        "Description": "Red Short",
        "ETA": 16
      },
      {
        "RouteStopId": 403,
        "Name": "His Majesty's",
        "Description": "Red Short",
        "ETA": 101
      },
      {
        "RouteStopId": 404,
        "Name": "QV1",
        "Description": "Red Short",
        "ETA": 186
      },
      {
        "RouteStopId": 405,
        "Name": "Freeway",
        "Description": "Red Short",
        "ETA": -1603863058
      },
      {
        "RouteStopId": 406,
        "Name": "Parliament",
        "Description": "Red Short",
        "ETA": 231
      },
      {
        "RouteStopId": 407,
        "Name": "Emerald Tce",
        "Description": "Red Short",
        "ETA": 316
      },
      {
        "RouteStopId": 408,
        "Name": "West Perth",
        "Description": "Red Short",
        "ETA": 401
      },
      {
        "RouteStopId": 409,
        "Name": "Outram Street",
        "Description": "Red Short",
        "ETA": 486
      },
      {
        "RouteStopId": 410,
        "Name": "Ord Street",
        "Description": "Red Short",
        "ETA": 33
      },
      {
        "RouteStopId": 411,
        "Name": "Havelock Street",
        "Description": "Red Short",
        "ETA": 118
      },
      {
        "RouteStopId": 412,
        "Name": "Gordon Street",
        "Description": "Red Short",
        "ETA": 203
      },
      {
        "RouteStopId": 413,
        "Name": "Milligan Street",
        "Description": "Red Short",
        "ETA": 288
      },
      {
        "RouteStopId": 414,
        "Name": "Raine Square",
        "Description": "Red Short",
        "ETA": 373
      },
      {
        "RouteStopId": 415,
        "Name": "Wellington Street Bus Station",
        "Description": "Red Short",
        "ETA": -1603863058
      },
      {
        "RouteStopId": 801,
        "Name": "Elizabeth Quay Bus Station",
        "Description": "Green",
        "ETA": 201
      },
      {
        "RouteStopId": 802,
        "Name": "Mill Street",
        "Description": "Green",
        "ETA": 921
      },
      {
        "RouteStopId": 803,
        "Name": "Milligan Street",
        "Description": "Green",
        "ETA": 981
      },
      {
        "RouteStopId": 804,
        "Name": "Harvest Tce",
        "Description": "Green",
        "ETA": 1081
      },
      {
        "RouteStopId": 805,
        "Name": "Havelock Street",
        "Description": "Green",
        "ETA": 1141
      },
      {
        "RouteStopId": 806,
        "Name": "Ord Street",
        "Description": "Green",
        "ETA": 1241
      },
      {
        "RouteStopId": 807,
        "Name": "Hay Street",
        "Description": "Green",
        "ETA": 1341
      },
      {
        "RouteStopId": 808,
        "Name": "Harold Boas Gardens",
        "Description": "Green",
        "ETA": 39
      },
      {
        "RouteStopId": 809,
        "Name": "Sutherland Street",
        "Description": "Green",
        "ETA": 139
      },
      {
        "RouteStopId": 810,
        "Name": "City West Station",
        "Description": "Green",
        "ETA": 239
      },
      {
        "RouteStopId": 811,
        "Name": "Leederville Station",
        "Description": "Green",
        "ETA": 469
      },
      {
        "RouteStopId": 812,
        "Name": "City West Station",
        "Description": "Green",
        "ETA": 182
      },
      {
        "RouteStopId": 813,
        "Name": "Sutherland Street",
        "Description": "Green",
        "ETA": 282
      },
      {
        "RouteStopId": 814,
        "Name": "Harold Boas Gardens",
        "Description": "Green",
        "ETA": 382
      },
      {
        "RouteStopId": 815,
        "Name": "Hay Street",
        "Description": "Green",
        "ETA": 482
      },
      {
        "RouteStopId": 816,
        "Name": "Kings Park Road",
        "Description": "Green",
        "ETA": 652
      },
      {
        "RouteStopId": 817,
        "Name": "Havelock Street",
        "Description": "Green",
        "ETA": 752
      },
      {
        "RouteStopId": 818,
        "Name": "Harvest Tce",
        "Description": "Green",
        "ETA": 852
      },
      {
        "RouteStopId": 819,
        "Name": "Milligan Street",
        "Description": "Green",
        "ETA": 952
      },
      {
        "RouteStopId": 820,
        "Name": "Cloisters",
        "Description": "Green",
        "ETA": 1142
      }
    ],
    "LastUpdated": "2020-10-28T13:30:57+08:00",
    "ShowBusCount": false
  }
}
