{
  "result": "success",
  "data": {
    "Buses": [
      {
        "RouteId": 2,
        "BusId": 2139,
        "ETA": 146,
        "LastStopId": 231,
        "NextStopId": 201,
        "LatLng": {
          "Latitude": -31.952255277922646,
          "Longitude": 115.86112249786696
        },
        "ImageUrl": "/Portals/0/Asset/Images/LiveCatTimes/redCat/bus_291.png",
        "ImageWidth": 40,
        "ImageHeight": 40
      },
      {
        "RouteId": 3,
        "BusId": 2140,
        "ETA": 15,
        "LastStopId": 330,
        "NextStopId": 331,
        "LatLng": {
          "Latitude": -31.949621724479844,
          "Longitude": 115.85294965482998
        },
        "ImageUrl": "/Portals/0/Asset/Images/LiveCatTimes/yellowCat/bus_290.png",
        "ImageWidth": 40,
        "ImageHeight": 40
      },
      {
        "RouteId": 1,
        "BusId": 2141,
        "ETA": 30,
        "LastStopId": 116,
        "NextStopId": 117,
        "LatLng": {
          "Latitude": -31.95108940032351,
          "Longitude": 115.8589428716932
        },
        "ImageUrl": "/Portals/0/Asset/Images/LiveCatTimes/blueCat/bus_274.png",
        "ImageWidth": 40,
        "ImageHeight": 40
      },
      {
        "RouteId": 3,
        "BusId": 2143,
        "ETA": 22,
        "LastStopId": 335,
        "NextStopId": 336,
        "LatLng": {
          "Latitude": -31.9482448189191,
          "Longitude": 115.8491877707483
        },
        "ImageUrl": "/Portals/0/Asset/Images/LiveCatTimes/yellowCat/bus_111.png",
        "ImageWidth": 40,
        "ImageHeight": 40
      },
      {
        "RouteId": 8,
        "BusId": 2144,
        "ETA": -152,
        "LastStopId": 820,
        "NextStopId": 801,
        "LatLng": {
          "Latitude": -31.95622176653301,
          "Longitude": 115.8544456128755
        },
        "ImageUrl": "/Portals/0/Asset/Images/LiveCatTimes/greenCat/bus_291.png",
        "ImageWidth": 40,
        "ImageHeight": 40
      },
      {
        "RouteId": 3,
        "BusId": 2145,
        "ETA": 7,
        "LastStopId": 314,
        "NextStopId": 315,
        "LatLng": {
          "Latitude": -31.95097854958378,
          "Longitude": 115.87049776708085
        },
        "ImageUrl": "/Portals/0/Asset/Images/LiveCatTimes/yellowCat/bus_91.png",
        "ImageWidth": 40,
        "ImageHeight": 40
      },
      {
        "RouteId": 2,
        "BusId": 2610,
        "ETA": -147,
        "LastStopId": 206,
        "NextStopId": 207,
        "LatLng": {
          "Latitude": -31.95871036787759,
          "Longitude": 115.87795895863822
        },
        "ImageUrl": "/Portals/0/Asset/Images/LiveCatTimes/redCat/bus_94.png",
        "ImageWidth": 40,
        "ImageHeight": 40
      },
      {
        "RouteId": 2,
        "BusId": 2619,
        "ETA": 151,
        "LastStopId": 229,
        "NextStopId": 231,
        "LatLng": {
          "Latitude": -31.95235517402741,
          "Longitude": 115.85714710893248
        },
        "ImageUrl": "/Portals/0/Asset/Images/LiveCatTimes/redCat/bus_110.png",
        "ImageWidth": 40,
        "ImageHeight": 40
      },
      {
        "RouteId": 2,
        "BusId": 2620,
        "ETA": 9,
        "LastStopId": 210,
        "NextStopId": 211,
        "LatLng": {
          "Latitude": -31.957483176304766,
          "Longitude": 115.86899874013454
        },
        "ImageUrl": "/Portals/0/Asset/Images/LiveCatTimes/redCat/bus_291.png",
        "ImageWidth": 40,
        "ImageHeight": 40
      },
      {
        "RouteId": 8,
        "BusId": 2621,
        "ETA": 77,
        "LastStopId": 808,
        "NextStopId": 809,
        "LatLng": {
          "Latitude": -31.94658255912853,
          "Longitude": 115.8439007751501
        },
        "ImageUrl": "/Portals/0/Asset/Images/LiveCatTimes/greenCat/bus_108.png",
        "ImageWidth": 40,
        "ImageHeight": 40
      },
      {
        "RouteId": 1,
        "BusId": 2622,
        "ETA": 56,
        "LastStopId": 122,
        "NextStopId": 198,
        "LatLng": {
          "Latitude": -31.95621,
          "Longitude": 115.85409
        },
        "ImageUrl": "/Portals/0/Asset/Images/LiveCatTimes/blueCat/bus_.png",
        "ImageWidth": 40,
        "ImageHeight": 40
      },
      {
        "RouteId": 2,
        "BusId": 2624,
        "ETA": 89,
        "LastStopId": 216,
        "NextStopId": 217,
        "LatLng": {
          "Latitude": -31.952859209624744,
          "Longitude": 115.85734662894308
        },
        "ImageUrl": "/Portals/0/Asset/Images/LiveCatTimes/redCat/bus_200.png",
        "ImageWidth": 40,
        "ImageHeight": 40
      },
      {
        "RouteId": 3,
        "BusId": 2625,
        "ETA": -7,
        "LastStopId": 332,
        "NextStopId": 333,
        "LatLng": {
          "Latitude": -31.94633820252914,
          "Longitude": 115.83935340926172
        },
        "ImageUrl": "/Portals/0/Asset/Images/LiveCatTimes/yellowCat/bus_287.png",
        "ImageWidth": 40,
        "ImageHeight": 40
      },
      {
        "RouteId": 1,
        "BusId": 2627,
        "ETA": 269,
        "LastStopId": 119,
        "NextStopId": 106,
        "LatLng": {
          "Latitude": -31.959572300058333,
          "Longitude": 115.85790202905578
        },
        "ImageUrl": "/Portals/0/Asset/Images/LiveCatTimes/blueCat/bus_288.png",
        "ImageWidth": 40,
        "ImageHeight": 40
      },
      {
        "RouteId": 2,
        "BusId": 2628,
        "ETA": 19,
        "LastStopId": 203,
        "NextStopId": 204,
        "LatLng": {
          "Latitude": -31.956240915759217,
          "Longitude": 115.86904951484762
        },
        "ImageUrl": "/Portals/0/Asset/Images/LiveCatTimes/redCat/bus_111.png",
        "ImageWidth": 40,
        "ImageHeight": 40
      },
      {
        "RouteId": 8,
        "BusId": 2629,
        "ETA": 75,
        "LastStopId": 811,
        "NextStopId": 812,
        "LatLng": {
          "Latitude": -31.940490459809375,
          "Longitude": 115.84122990315441
        },
        "ImageUrl": "/Portals/0/Asset/Images/LiveCatTimes/greenCat/bus_130.png",
        "ImageWidth": 40,
        "ImageHeight": 40
      },
      {
        "RouteId": 3,
        "BusId": 2630,
        "ETA": 68,
        "LastStopId": 306,
        "NextStopId": 307,
        "LatLng": {
          "Latitude": -31.954895993600456,
          "Longitude": 115.86914798069819
        },
        "ImageUrl": "/Portals/0/Asset/Images/LiveCatTimes/yellowCat/bus_291.png",
        "ImageWidth": 40,
        "ImageHeight": 40
      },
      {
        "RouteId": 8,
        "BusId": 2631,
        "ETA": 106,
        "LastStopId": 815,
        "NextStopId": 816,
        "LatLng": {
          "Latitude": -31.94905601883711,
          "Longitude": 115.84201696693158
        },
        "ImageUrl": "/Portals/0/Asset/Images/LiveCatTimes/greenCat/bus_203.png",
        "ImageWidth": 40,
        "ImageHeight": 40
      },
      {
        "RouteId": 2,
        "BusId": 2632,
        "ETA": 27,
        "LastStopId": 213,
        "NextStopId": 215,
        "LatLng": {
          "Latitude": -31.954668983450162,
          "Longitude": 115.86035789210928
        },
        "ImageUrl": "/Portals/0/Asset/Images/LiveCatTimes/redCat/bus_290.png",
        "ImageWidth": 40,
        "ImageHeight": 40
      },
      {
        "RouteId": 2,
        "BusId": 2635,
        "ETA": -20,
        "LastStopId": 218,
        "NextStopId": 219,
        "LatLng": {
          "Latitude": -31.95174603683763,
          "Longitude": 115.85133230767644
        },
        "ImageUrl": "/Portals/0/Asset/Images/LiveCatTimes/redCat/bus_291.png",
        "ImageWidth": 40,
        "ImageHeight": 40
      },
      {
        "RouteId": 1,
        "BusId": 2665,
        "ETA": 70,
        "LastStopId": 109,
        "NextStopId": 110,
        "LatLng": {
          "Latitude": -31.947517472280634,
          "Longitude": 115.86104835189664
        },
        "ImageUrl": "/Portals/0/Asset/Images/LiveCatTimes/blueCat/bus_298.png",
        "ImageWidth": 40,
        "ImageHeight": 40
      },
      {
        "RouteId": 1,
        "BusId": 2666,
        "ETA": 7,
        "LastStopId": 117,
        "NextStopId": 122,
        "LatLng": {
          "Latitude": -31.955637669260845,
          "Longitude": 115.85609655941862
        },
        "ImageUrl": "/Portals/0/Asset/Images/LiveCatTimes/blueCat/bus_200.png",
        "ImageWidth": 40,
        "ImageHeight": 40
      },
      {
        "RouteId": 3,
        "BusId": 2667,
        "ETA": 36,
        "LastStopId": 310,
        "NextStopId": 311,
        "LatLng": {
          "Latitude": -31.955359994799363,
          "Longitude": 115.88014
        },
        "ImageUrl": "/Portals/0/Asset/Images/LiveCatTimes/yellowCat/bus_0.png",
        "ImageWidth": 40,
        "ImageHeight": 40
      },
      {
        "RouteId": 2,
        "BusId": 2668,
        "ETA": 15,
        "LastStopId": 224,
        "NextStopId": 225,
        "LatLng": {
          "Latitude": -31.949543033802478,
          "Longitude": 115.83926851226765
        },
        "ImageUrl": "/Portals/0/Asset/Images/LiveCatTimes/redCat/bus_200.png",
        "ImageWidth": 40,
        "ImageHeight": 40
      },
      {
        "RouteId": 3,
        "BusId": 2669,
        "ETA": 23,
        "LastStopId": 326,
        "NextStopId": 327,
        "LatLng": {
          "Latitude": -31.953645186405776,
          "Longitude": 115.86540528379732
        },
        "ImageUrl": "/Portals/0/Asset/Images/LiveCatTimes/yellowCat/bus_291.png",
        "ImageWidth": 40,
        "ImageHeight": 40
      },
      {
        "RouteId": 3,
        "BusId": 2670,
        "ETA": -168,
        "LastStopId": 315,
        "NextStopId": 316,
        "LatLng": {
          "Latitude": -31.951025110869075,
          "Longitude": 115.87128511087023
        },
        "ImageUrl": "/Portals/0/Asset/Images/LiveCatTimes/yellowCat/bus_139.png",
        "ImageWidth": 40,
        "ImageHeight": 40
      },
      {
        "RouteId": 2,
        "BusId": 2672,
        "ETA": -4,
        "LastStopId": 205,
        "NextStopId": 206,
        "LatLng": {
          "Latitude": -31.95864,
          "Longitude": 115.87794
        },
        "ImageUrl": "/Portals/0/Asset/Images/LiveCatTimes/redCat/bus_.png",
        "ImageWidth": 40,
        "ImageHeight": 40
      },
      {
        "RouteId": 2,
        "BusId": 2673,
        "ETA": 158,
        "LastStopId": 226,
        "NextStopId": 227,
        "LatLng": {
          "Latitude": -31.951449201369115,
          "Longitude": 115.84339872220391
        },
        "ImageUrl": "/Portals/0/Asset/Images/LiveCatTimes/redCat/bus_110.png",
        "ImageWidth": 40,
        "ImageHeight": 40
      },
      {
        "RouteId": 8,
        "BusId": 2674,
        "ETA": 137,
        "LastStopId": 820,
        "NextStopId": 801,
        "LatLng": {
          "Latitude": -31.956219981383686,
          "Longitude": 115.85444021071423
        },
        "ImageUrl": "/Portals/0/Asset/Images/LiveCatTimes/greenCat/bus_291.png",
        "ImageWidth": 40,
        "ImageHeight": 40
      },
      {
        "RouteId": 3,
        "BusId": 2675,
        "ETA": -29,
        "LastStopId": 332,
        "NextStopId": 333,
        "LatLng": {
          "Latitude": -31.94625734645148,
          "Longitude": 115.83908894118834
        },
        "ImageUrl": "/Portals/0/Asset/Images/LiveCatTimes/yellowCat/bus_111.png",
        "ImageWidth": 40,
        "ImageHeight": 40
      },
      {
        "RouteId": 8,
        "BusId": 2676,
        "ETA": 668,
        "LastStopId": 810,
        "NextStopId": 811,
        "LatLng": {
          "Latitude": -31.943025669136638,
          "Longitude": 115.84098376331853
        },
        "ImageUrl": "/Portals/0/Asset/Images/LiveCatTimes/greenCat/bus_289.png",
        "ImageWidth": 40,
        "ImageHeight": 40
      }
    ],
    "Stops": [
      {
        "RouteStopId": 101,
        "Name": "N/A",
        "Description": "Blue",
        "ETA": -1602487502
      },
      {
        "RouteStopId": 102,
        "Name": "N/A",
        "Description": "Blue",
        "ETA": -1602487502
      },
      {
        "RouteStopId": 103,
        "Name": "N/A",
        "Description": "Blue",
        "ETA": -1602487502
      },
      {
        "RouteStopId": 104,
        "Name": "N/A",
        "Description": "Blue",
        "ETA": -1602487502
      },
      {
        "RouteStopId": 105,
        "Name": "N/A",
        "Description": "Blue",
        "ETA": -1602487502
      },
      {
        "RouteStopId": 106,
        "Name": "Beaufort St Bridge",
        "Description": "Blue",
        "ETA": 270
      },
      {
        "RouteStopId": 107,
        "Name": "Museum",
        "Description": "Blue",
        "ETA": 370
      },
      {
        "RouteStopId": 108,
        "Name": "Arts Centre",
        "Description": "Blue",
        "ETA": 470
      },
      {
        "RouteStopId": 109,
        "Name": "Central Institute",
        "Description": "Blue",
        "ETA": 570
      },
      {
        "RouteStopId": 110,
        "Name": "Aberdeen Street",
        "Description": "Blue",
        "ETA": 71
      },
      {
        "RouteStopId": 111,
        "Name": "Francis Street",
        "Description": "Blue",
        "ETA": 171
      },
      {
        "RouteStopId": 112,
        "Name": "Russell Square",
        "Description": "Blue",
        "ETA": 271
      },
      {
        "RouteStopId": 113,
        "Name": "Northbridge",
        "Description": "Blue",
        "ETA": 371
      },
      {
        "RouteStopId": 114,
        "Name": "James Street",
        "Description": "Blue",
        "ETA": 471
      },
      {
        "RouteStopId": 116,
        "Name": "Horseshoe Bridge",
        "Description": "Blue",
        "ETA": 571
      },
      {
        "RouteStopId": 117,
        "Name": "Perth Underground",
        "Description": "Blue",
        "ETA": 31
      },
      {
        "RouteStopId": 118,
        "Name": "N/A",
        "Description": "Blue",
        "ETA": -1602487502
      },
      {
        "RouteStopId": 119,
        "Name": "Barrack Square",
        "Description": "Blue",
        "ETA": 299
      },
      {
        "RouteStopId": 120,
        "Name": "N/A",
        "Description": "Blue",
        "ETA": -1602487502
      },
      {
        "RouteStopId": 121,
        "Name": "N/A",
        "Description": "Blue",
        "ETA": -1602487502
      },
      {
        "RouteStopId": 122,
        "Name": "Elizabeth Quay Bus Station",
        "Description": "Blue",
        "ETA": 8
      },
      {
        "RouteStopId": 123,
        "Name": "N/A",
        "Description": "Blue",
        "ETA": -1602487502
      },
      {
        "RouteStopId": 198,
        "Name": "N/A",
        "Description": "Blue",
        "ETA": 57
      },
      {
        "RouteStopId": 199,
        "Name": "N/A",
        "Description": "Blue",
        "ETA": -1602487502
      },
      {
        "RouteStopId": 201,
        "Name": "Murray Street",
        "Description": "Red",
        "ETA": 147
      },
      {
        "RouteStopId": 202,
        "Name": "Royal Perth Hospital",
        "Description": "Red",
        "ETA": 247
      },
      {
        "RouteStopId": 203,
        "Name": "Mercedes College",
        "Description": "Red",
        "ETA": 347
      },
      {
        "RouteStopId": 204,
        "Name": "Bennet Street",
        "Description": "Red",
        "ETA": 20
      },
      {
        "RouteStopId": 205,
        "Name": "Queens Gardens",
        "Description": "Red",
        "ETA": 133
      },
      {
        "RouteStopId": 206,
        "Name": "WACA",
        "Description": "Red",
        "ETA": -3
      },
      {
        "RouteStopId": 207,
        "Name": "Don Aitken Centre",
        "Description": "Red",
        "ETA": -146
      },
      {
        "RouteStopId": 208,
        "Name": "Plain Street",
        "Description": "Red",
        "ETA": -46
      },
      {
        "RouteStopId": 209,
        "Name": "Wellington Square",
        "Description": "Red",
        "ETA": 54
      },
      {
        "RouteStopId": 210,
        "Name": "Carlton",
        "Description": "Red",
        "ETA": 184
      },
      {
        "RouteStopId": 211,
        "Name": "Perth Mint",
        "Description": "Red",
        "ETA": 10
      },
      {
        "RouteStopId": 212,
        "Name": "Victoria Avenue",
        "Description": "Red",
        "ETA": 110
      },
      {
        "RouteStopId": 213,
        "Name": "Town Hall",
        "Description": "Red",
        "ETA": 230
      },
      {
        "RouteStopId": 214,
        "Name": "Murray St Mall East",
        "Description": "Red",
        "ETA": -1602487502
      },
      {
        "RouteStopId": 215,
        "Name": "Forrest Place",
        "Description": "Red",
        "ETA": 28
      },
      {
        "RouteStopId": 216,
        "Name": "Perth Underground",
        "Description": "Red",
        "ETA": 158
      },
      {
        "RouteStopId": 217,
        "Name": "Central Park",
        "Description": "Red",
        "ETA": 90
      },
      {
        "RouteStopId": 218,
        "Name": "His Majesty's",
        "Description": "Red",
        "ETA": 220
      },
      {
        "RouteStopId": 219,
        "Name": "QV1",
        "Description": "Red",
        "ETA": -19
      },
      {
        "RouteStopId": 220,
        "Name": "Freeway",
        "Description": "Red",
        "ETA": -1602487502
      },
      {
        "RouteStopId": 221,
        "Name": "Parliament",
        "Description": "Red",
        "ETA": 71
      },
      {
        "RouteStopId": 222,
        "Name": "Emerald Tce",
        "Description": "Red",
        "ETA": 171
      },
      {
        "RouteStopId": 223,
        "Name": "West Perth",
        "Description": "Red",
        "ETA": 271
      },
      {
        "RouteStopId": 224,
        "Name": "Outram Street",
        "Description": "Red",
        "ETA": 356
      },
      {
        "RouteStopId": 225,
        "Name": "Ord Street",
        "Description": "Red",
        "ETA": 16
      },
      {
        "RouteStopId": 226,
        "Name": "Havelock Street",
        "Description": "Red",
        "ETA": 116
      },
      {
        "RouteStopId": 227,
        "Name": "Gordon Street",
        "Description": "Red",
        "ETA": 159
      },
      {
        "RouteStopId": 228,
        "Name": "Milligan Street",
        "Description": "Red",
        "ETA": 274
      },
      {
        "RouteStopId": 229,
        "Name": "Raine Square",
        "Description": "Red",
        "ETA": 434
      },
      {
        "RouteStopId": 230,
        "Name": "Wellington Street Bus Station",
        "Description": "Red",
        "ETA": -1602487502
      },
      {
        "RouteStopId": 231,
        "Name": "Perth Train Station",
        "Description": "Red",
        "ETA": 152
      },
      {
        "RouteStopId": 232,
        "Name": "Perth Arena",
        "Description": "Red",
        "ETA": -1602487502
      },
      {
        "RouteStopId": 299,
        "Name": "Temporary Stop",
        "Description": "Red",
        "ETA": -1602487502
      },
      {
        "RouteStopId": 302,
        "Name": "Yagan Sq.",
        "Description": "Yellow",
        "ETA": 108
      },
      {
        "RouteStopId": 303,
        "Name": "Perth Train Station (Yellow)",
        "Description": "Yellow",
        "ETA": 193
      },
      {
        "RouteStopId": 304,
        "Name": "Pier Street",
        "Description": "Yellow",
        "ETA": 293
      },
      {
        "RouteStopId": 305,
        "Name": "Royal Perth Hospital North",
        "Description": "Yellow",
        "ETA": 378
      },
      {
        "RouteStopId": 306,
        "Name": "Wellington Fair",
        "Description": "Yellow",
        "ETA": 463
      },
      {
        "RouteStopId": 307,
        "Name": "Wellington Square North",
        "Description": "Yellow",
        "ETA": 69
      },
      {
        "RouteStopId": 308,
        "Name": "Police Traffic Branch",
        "Description": "Yellow",
        "ETA": 154
      },
      {
        "RouteStopId": 309,
        "Name": "Main Roads",
        "Description": "Yellow",
        "ETA": 239
      },
      {
        "RouteStopId": 310,
        "Name": "East Perth Cemeteries",
        "Description": "Yellow",
        "ETA": 324
      },
      {
        "RouteStopId": 311,
        "Name": "Haig Park Circle",
        "Description": "Yellow",
        "ETA": 37
      },
      {
        "RouteStopId": 312,
        "Name": "Regal Place",
        "Description": "Yellow",
        "ETA": 122
      },
      {
        "RouteStopId": 313,
        "Name": "Education Department",
        "Description": "Yellow",
        "ETA": 207
      },
      {
        "RouteStopId": 314,
        "Name": "Health Department",
        "Description": "Yellow",
        "ETA": 292
      },
      {
        "RouteStopId": 315,
        "Name": "Claisebrook Station",
        "Description": "Yellow",
        "ETA": 8
      },
      {
        "RouteStopId": 316,
        "Name": "Royal Street Car Park",
        "Description": "Yellow",
        "ETA": -167
      },
      {
        "RouteStopId": 317,
        "Name": "Central Institute",
        "Description": "Yellow",
        "ETA": -82
      },
      {
        "RouteStopId": 318,
        "Name": "Royal Square",
        "Description": "Yellow",
        "ETA": 3
      },
      {
        "RouteStopId": 319,
        "Name": "Victoria Gardens",
        "Description": "Yellow",
        "ETA": 88
      },
      {
        "RouteStopId": 320,
        "Name": "Nile Street",
        "Description": "Yellow",
        "ETA": 173
      },
      {
        "RouteStopId": 321,
        "Name": "Don Aitken Centre",
        "Description": "Yellow",
        "ETA": 258
      },
      {
        "RouteStopId": 322,
        "Name": "Plain Street",
        "Description": "Yellow",
        "ETA": 343
      },
      {
        "RouteStopId": 323,
        "Name": "Wellington Square",
        "Description": "Yellow",
        "ETA": 416
      },
      {
        "RouteStopId": 324,
        "Name": "Hill Street",
        "Description": "Yellow",
        "ETA": 501
      },
      {
        "RouteStopId": 325,
        "Name": "Lord Street",
        "Description": "Yellow",
        "ETA": 586
      },
      {
        "RouteStopId": 326,
        "Name": "Royal Perth Hospital South",
        "Description": "Yellow",
        "ETA": 671
      },
      {
        "RouteStopId": 327,
        "Name": "Western Power",
        "Description": "Yellow",
        "ETA": 24
      },
      {
        "RouteStopId": 328,
        "Name": "Forrest Place",
        "Description": "Yellow",
        "ETA": 109
      },
      {
        "RouteStopId": 329,
        "Name": "Raine Square",
        "Description": "Yellow",
        "ETA": 194
      },
      {
        "RouteStopId": 330,
        "Name": "Perth Arena",
        "Description": "Yellow",
        "ETA": 239
      },
      {
        "RouteStopId": 331,
        "Name": "Sutherland Street",
        "Description": "Yellow",
        "ETA": 16
      },
      {
        "RouteStopId": 332,
        "Name": "Colin Street North",
        "Description": "Yellow",
        "ETA": 186
      },
      {
        "RouteStopId": 333,
        "Name": "Thomas Street",
        "Description": "Yellow",
        "ETA": -28
      },
      {
        "RouteStopId": 334,
        "Name": "Harold Boas North",
        "Description": "Yellow",
        "ETA": 57
      },
      {
        "RouteStopId": 335,
        "Name": "Sutherland Street",
        "Description": "Yellow",
        "ETA": 142
      },
      {
        "RouteStopId": 336,
        "Name": "Perth Arena",
        "Description": "Yellow",
        "ETA": 23
      },
      {
        "RouteStopId": 337,
        "Name": "Harold Boas South",
        "Description": "Yellow",
        "ETA": 101
      },
      {
        "RouteStopId": 401,
        "Name": "Perth Underground",
        "Description": "Red Short",
        "ETA": -118
      },
      {
        "RouteStopId": 402,
        "Name": "Central Park",
        "Description": "Red Short",
        "ETA": -33
      },
      {
        "RouteStopId": 403,
        "Name": "His Majesty's",
        "Description": "Red Short",
        "ETA": 52
      },
      {
        "RouteStopId": 404,
        "Name": "QV1",
        "Description": "Red Short",
        "ETA": 137
      },
      {
        "RouteStopId": 405,
        "Name": "Freeway",
        "Description": "Red Short",
        "ETA": -1602487502
      },
      {
        "RouteStopId": 406,
        "Name": "Parliament",
        "Description": "Red Short",
        "ETA": 182
      },
      {
        "RouteStopId": 407,
        "Name": "Emerald Tce",
        "Description": "Red Short",
        "ETA": 267
      },
      {
        "RouteStopId": 408,
        "Name": "West Perth",
        "Description": "Red Short",
        "ETA": 352
      },
      {
        "RouteStopId": 409,
        "Name": "Outram Street",
        "Description": "Red Short",
        "ETA": 437
      },
      {
        "RouteStopId": 410,
        "Name": "Ord Street",
        "Description": "Red Short",
        "ETA": 522
      },
      {
        "RouteStopId": 411,
        "Name": "Havelock Street",
        "Description": "Red Short",
        "ETA": 607
      },
      {
        "RouteStopId": 412,
        "Name": "Gordon Street",
        "Description": "Red Short",
        "ETA": 14
      },
      {
        "RouteStopId": 413,
        "Name": "Milligan Street",
        "Description": "Red Short",
        "ETA": 99
      },
      {
        "RouteStopId": 414,
        "Name": "Raine Square",
        "Description": "Red Short",
        "ETA": 184
      },
      {
        "RouteStopId": 415,
        "Name": "Wellington Street Bus Station",
        "Description": "Red Short",
        "ETA": -1602487502
      },
      {
        "RouteStopId": 801,
        "Name": "Elizabeth Quay Bus Station",
        "Description": "Green",
        "ETA": 138
      },
      {
        "RouteStopId": 802,
        "Name": "Mill Street",
        "Description": "Green",
        "ETA": 858
      },
      {
        "RouteStopId": 803,
        "Name": "Milligan Street",
        "Description": "Green",
        "ETA": 918
      },
      {
        "RouteStopId": 804,
        "Name": "Harvest Tce",
        "Description": "Green",
        "ETA": 1018
      },
      {
        "RouteStopId": 805,
        "Name": "Havelock Street",
        "Description": "Green",
        "ETA": 1078
      },
      {
        "RouteStopId": 806,
        "Name": "Ord Street",
        "Description": "Green",
        "ETA": 1178
      },
      {
        "RouteStopId": 807,
        "Name": "Hay Street",
        "Description": "Green",
        "ETA": 1278
      },
      {
        "RouteStopId": 808,
        "Name": "Harold Boas Gardens",
        "Description": "Green",
        "ETA": 1378
      },
      {
        "RouteStopId": 809,
        "Name": "Sutherland Street",
        "Description": "Green",
        "ETA": 78
      },
      {
        "RouteStopId": 810,
        "Name": "City West Station",
        "Description": "Green",
        "ETA": 178
      },
      {
        "RouteStopId": 811,
        "Name": "Leederville Station",
        "Description": "Green",
        "ETA": 408
      },
      {
        "RouteStopId": 812,
        "Name": "City West Station",
        "Description": "Green",
        "ETA": 669
      },
      {
        "RouteStopId": 813,
        "Name": "Sutherland Street",
        "Description": "Green",
        "ETA": 769
      },
      {
        "RouteStopId": 814,
        "Name": "Harold Boas Gardens",
        "Description": "Green",
        "ETA": 869
      },
      {
        "RouteStopId": 815,
        "Name": "Hay Street",
        "Description": "Green",
        "ETA": 969
      },
      {
        "RouteStopId": 816,
        "Name": "Kings Park Road",
        "Description": "Green",
        "ETA": 107
      },
      {
        "RouteStopId": 817,
        "Name": "Havelock Street",
        "Description": "Green",
        "ETA": 167
      },
      {
        "RouteStopId": 818,
        "Name": "Harvest Tce",
        "Description": "Green",
        "ETA": 267
      },
      {
        "RouteStopId": 819,
        "Name": "Milligan Street",
        "Description": "Green",
        "ETA": 367
      },
      {
        "RouteStopId": 820,
        "Name": "Cloisters",
        "Description": "Green",
        "ETA": 557
      }
    ],
    "LastUpdated": "2020-10-12T15:25:01+08:00",
    "ShowBusCount": false
  }
}
